LICENSE
README.md
netstring.py
setup.cfg
setup.py
python_netstring.egg-info/PKG-INFO
python_netstring.egg-info/SOURCES.txt
python_netstring.egg-info/dependency_links.txt
python_netstring.egg-info/top_level.txt