Metadata-Version: 2.1
Name: python-netstring
Version: 0.1.0
Summary: Pure python netstring protocol
Home-page: https://github.com/tiagocoutinho/netstring
Author: Jose Tiago Macara Coutinho
Author-email: coutinhotiago@gmail.com
License: UNKNOWN
Project-URL: Bug Tracker, https://github.com/tiagocoutinho/netstring/issues
Keywords: netstring
Platform: UNKNOWN
Classifier: Development Status :: 4 - Beta
Classifier: Intended Audience :: Developers
Classifier: Programming Language :: Python :: 3
Classifier: Operating System :: OS Independent
Classifier: License :: OSI Approved :: GNU General Public License v3 (GPLv3)
License-File: LICENSE
